design/writeback_buffer.sv
/*
    Module: Writeback Buffer 

    Description: FIFO buffer, implemented as a circular array 
    pushes data to the tail, and pops from the head. Outputs full signal 
    for when queue is full. Dirty Cache evictions are stored here to reduce latency 
    and opportunistically drained to the memory to ensure coherence. This module 
    also searches for matching entries and returns upon hits. Stores to the same 
    address are coalesced by skipping the draining of newer entries and adding the 
    new store to the tail.  

*/

module writeback_buffer #(
    parameter int DEPTH = 8, 
    parameter int DWIDTH = 32,
    parameter int AWIDTH = 32
)(
    input logic reset, 
    input logic clk,
    input logic [(DWIDTH+AWIDTH)-1:0] push_data,
    input logic [1:0] push_pop,
    input logic [AWIDTH-1:0] search_addr,
    input logic [POINTER_BITS:0] merge_entry,
    
    output logic drain_rq, 
    output logic [POINTER_BITS:0] found_entry, 
    output logic [DWIDTH-1:0] found_data,
    output logic found,
    output logic [DWIDTH-1:0] pop_data,
    output logic buffer_full 
);



// Push_Pop States 
parameter NO_OP = 0, PUSH = 1, POP = 2, MERGE = 3; 

// FIFO Buffer 
logic [(DWIDTH+AWIDTH):0] fifo_buffer [0:DEPTH-1];

// Pointers 
parameter int POINTER_BITS = $clog2(DEPTH);
logic [POINTER_BITS:0] head; 
logic [POINTER_BITS:0] tail;

// Empty flag 
logic empty; 

assign drain_rq = !(empty); 

// Search Logic 
always_comb begin 
    found = 0; 
    found_entry = 0; 
    found_data = 0;

    for(int i=0; i<DEPTH; i++) begin 
        if ((fifo_buffer[i][(DWIDTH+AWIDTH)-1:DWIDTH] == search_addr) && (fifo_buffer[i][DWIDTH+AWIDTH] != 1)) begin
            found = 1; 
            found_entry = i; 
            found_data = fifo_buffer[i][DWIDTH-1:0];
        end
    end
end 


// Full and Empty Detection Logic 
always_comb begin

    if (head == tail) begin 
        empty = 1; 
        buffer_full = 0; 
    end

    else if (head[POINTER_BITS] ^ tail[POINTER_BITS]) begin 
        if (head[POINTER_BITS-1:0] == tail[POINTER_BITS-1:0]) begin
            buffer_full = 1; 
        end
        else begin
            buffer_full = 0;
        end
        empty = 0; 
    end

    else begin
        empty = 0; 
        buffer_full = 0; 
    end

end

// Push and Pop logic 
always_ff @(posedge clk) begin

    if (!reset) begin
        tail <= 0; 
        head <= 0; 
        for (int i=0; i<DEPTH; i++) begin 
            fifo_buffer[i] <= 0; 
        end 
    end

    else begin 
        unique case(push_pop)

            NO_OP:begin
                tail <= tail; 
                head <= head; 
                pop_data <= 0; 
            end

            PUSH: begin
                if(!buffer_full) begin
                    fifo_buffer[tail[POINTER_BITS-1:0]] <= push_data;
                    tail <= tail+1; 
                end
                pop_data <= 0; 
            end

            POP: begin
                if (!empty) begin
                    pop_data <= fifo_buffer[head[POINTER_BITS-1:0]];
                    head <= head+1;
                    fifo_buffer[head[POINTER_BITS-1:0]][DWIDTH+AWIDTH] <= 1; 
                end
                else begin 
                    pop_data <= 0; 
                end
            end

            MERGE: begin 
               if(!buffer_full) begin
                    fifo_buffer[tail[POINTER_BITS-1:0]] <= push_data;
                    tail <= tail+1; 
                end
                fifo_buffer[merge_entry[POINTER_BITS-1:0]][DWIDTH+AWIDTH] <= 1; 
                pop_data <= 0; 
            end 

            default: begin
                tail <= tail; 
                head <= head; 
                pop_data <= 0;
            end

        endcase
    end
end 


endmodule : writeback_buffer

test/fifo_tb.sv



module fifo_tb; 

logic clk; 
logic reset; 
logic [11:0] push_data; 
logic [1:0] push_pop; 
logic [3:0] search_addr;
logic [2:0] merge_entry; 

logic drain_rq; 
logic found_entry; 
logic found;
logic [11:0] pop_data; 
logic [7:0] found_data; 
logic buffer_full;


writeback_buffer #(
    .DEPTH(4), 
    .DWIDTH(8),
    .AWIDTH(4)
    ) fifo1 (.*); 


initial begin 
    clk=0; 
    reset=0;
    push_data=0; 
    push_pop=0; 
    search_addr=0;
    merge_entry=0; 
end

always #1 clk = ~clk;



// simulation 
initial begin 
    $display("SIMULATION START"); 
    #3
    reset=1; 
    search_addr = 4'b1000; 
    // PUSH X
    push_pop = 1; 
    push_data = 12'b100010101010;
    #2
    // PUSH Y
    push_pop = 1; 
    push_data = 12'b101010101010;
    #2
    // PUSH Z
    push_pop = 1; 
    push_data = 12'b100110101010;
    #2 
    // MERGE X
    push_pop = 3; 
    push_data = 12'b100010100000;
    merge_entry = 3'b000; 
    #2
    // POP
    push_pop = 2; 
    #2 
    // PUSH A
    push_pop = 1; 
    push_data = 12'b110010101010;
    #2 
    // PUSH B
    push_pop = 1; 
    push_data = 12'b100010101010;
    #2 
    // POP
    push_pop = 2; 
    #2 
    // POP 
    push_pop = 2; 
    #2
    // POP
    push_pop = 2; 
    #2 
    // PUSH X 
    push_pop = 1; 
    push_data = 12'b100010101010;
    #2
    // MERGE X
    push_pop = 3; 
    push_data = 12'b100010100000;
    merge_entry = 3'b001;
    #2
    // MERGE X
    push_pop = 3; 
    push_data = 12'b100010111111;
    merge_entry = 3'b010;  
    #2
    $finish; 
end 

initial begin 
    $dumpfile("fifo.vcd");
    $dumpvars(0, fifo_tb);  
end

endmodule

fifo.vcd
$version Generated by VerilatedVcd $end
$timescale 1ps $end
 $scope module fifo_tb $end
  $var wire 1 4 clk $end
  $var wire 1 # reset $end
  $var wire 12 $ push_data [11:0] $end
  $var wire 2 % push_pop [1:0] $end
  $var wire 4 & search_addr [3:0] $end
  $var wire 3 ' merge_entry [2:0] $end
  $var wire 1 ( drain_rq $end
  $var wire 1 5 found_entry $end
  $var wire 1 6 found $end
  $var wire 12 ) pop_data [11:0] $end
  $var wire 8 7 found_data [7:0] $end
  $var wire 1 * buffer_full $end
  $scope module fifo1 $end
   $var wire 32 9 DEPTH [31:0] $end
   $var wire 32 : DWIDTH [31:0] $end
   $var wire 32 9 AWIDTH [31:0] $end
   $var wire 1 # reset $end
   $var wire 1 4 clk $end
   $var wire 12 $ push_data [11:0] $end
   $var wire 2 % push_pop [1:0] $end
   $var wire 4 & search_addr [3:0] $end
   $var wire 3 ' merge_entry [2:0] $end
   $var wire 1 ( drain_rq $end
   $var wire 3 8 found_entry [2:0] $end
   $var wire 8 7 found_data [7:0] $end
   $var wire 1 6 found $end
   $var wire 8 + pop_data [7:0] $end
   $var wire 1 * buffer_full $end
   $var wire 32 ; NO_OP [31:0] $end
   $var wire 32 < PUSH [31:0] $end
   $var wire 32 = POP [31:0] $end
   $var wire 32 > MERGE [31:0] $end
   $var wire 13 , fifo_buffer[0] [12:0] $end
   $var wire 13 - fifo_buffer[1] [12:0] $end
   $var wire 13 . fifo_buffer[2] [12:0] $end
   $var wire 13 / fifo_buffer[3] [12:0] $end
   $var wire 32 ? POINTER_BITS [31:0] $end
   $var wire 3 0 head [2:0] $end
   $var wire 3 1 tail [2:0] $end
   $var wire 1 2 empty $end
   $scope module unnamedblk1 $end
    $var wire 32 @ i [31:0] $end
   $upscope $end
   $scope module unnamedblk2 $end
    $var wire 32 3 i [31:0] $end
   $upscope $end
  $upscope $end
 $upscope $end
$enddefinitions $end


#0
0#
b000000000000 $
b00 %
b0000 &
b000 '
0(
b000000000000 )
0*
b00000000 +
b0000000000000 ,
b0000000000000 -
b0000000000000 .
b0000000000000 /
b000 0
b000 1
12
b00000000000000000000000000000000 3
04
15
16
b00000000 7
b011 8
b00000000000000000000000000000100 9
b00000000000000000000000000001000 :
b00000000000000000000000000000000 ;
b00000000000000000000000000000001 <
b00000000000000000000000000000010 =
b00000000000000000000000000000011 >
b00000000000000000000000000000010 ?
b00000000000000000000000000000100 @
#1
b00000000000000000000000000000100 3
14
#2
04
#3
1#
b100010101010 $
b01 %
b1000 &
1(
b0100010101010 ,
b001 1
02
14
05
b10101010 7
b000 8
#4
04
#5
b101010101010 $
b0101010101010 -
b010 1
14
#6
04
#7
b100110101010 $
b0100110101010 .
b011 1
14
#8
04
#9
b100010100000 $
b11 %
1*
b1100010101010 ,
b0100010100000 /
b100 1
14
15
b10100000 7
b011 8
#10
04
#11
b10 %
b000010101010 )
0*
b10101010 +
b001 0
14
#12
04
#13
b110010101010 $
b01 %
b000000000000 )
1*
b00000000 +
b0110010101010 ,
b101 1
14
#14
04
#15
b100010101010 $
14
#16
04
#17
b10 %
b000010101010 )
0*
b10101010 +
b1101010101010 -
b010 0
14
#18
04
#19
b1100110101010 .
b011 0
14
#20
04
#21
b000010100000 )
b10100000 +
b1100010100000 /
b100 0
14
05
06
b00000000 7
b000 8
#22
04
#23
b01 %
b000000000000 )
b00000000 +
b0100010101010 -
b110 1
14
15
16
b10101010 7
b001 8
#24
04
#25
b100010100000 $
b11 %
b001 '
b1100010101010 -
b0100010100000 .
b111 1
14
05
b10100000 7
b010 8
#26
04
#27
b100010111111 $
b010 '
1*
b1100010100000 .
b0100010111111 /
b000 1
14
15
b10111111 7
b011 8
