design/constants.svh
`ifndef CONSTANTS_SVH_
`define CONSTANTS_SVH_

parameter logic [31:0] ZERO = 32'd0;

    // Opcode group definitions (RV32I base ISA)
    // Constants.svh not working here, so redefining
    parameter logic [6:0]
        OP_R         = 7'b0110011, // R-type
        OP_I         = 7'b0010011, // I-type arithmetic
        OP_LOAD      = 7'b0000011, // Load
        OP_STORE     = 7'b0100011, // Store
        OP_WRITEBACK = 7'b1111111,
        OP_EVICT    = 7'b1100011, // Branch
        OP_JALR      = 7'b1100111, // Jump register
        OP_JAL       = 7'b1101111, // Jump and link
        OP_LUI       = 7'b0110111, // Load upper immediate
        OP_AUIPC     = 7'b0010111; // Add upper immediate to PC

    // ALU operation encodings
    parameter logic [3:0]
        ALU_ADD = 4'd0,
        ALU_SUB = 4'd1,
        ALU_AND = 4'd2,
        ALU_OR  = 4'd3,
        ALU_XOR = 4'd4,
        ALU_SLT = 4'd5,
        ALU_SLL = 4'd6,
        ALU_SRL = 4'd7,
        ALU_SRA = 4'd8,
        ALU_LUI = 4'd9,
        ALU_BRANCH = 4'd10,
        ALU_NOP = 4'd15;

`endif

design/memory.sv
/*
 * Module: memory
 *
 * Description: Byte-addressable memory implementation. Supports both read and write operations.
 * Reads are combinational and writes are performed on the rising clock edge.
 *
 * Inputs:
 * 1) clk
 * 2) rst signal
 * 3) AWIDTH address addr_i
 * 4) DWIDTH data to write data_i
 * 5) read enable signal read_en_i
 * 6) write enable signal write_en_i
 *
 * Outputs:
 * 1) DWIDTH data output data_o
 */

module memory #(
  // parameters
  parameter int AWIDTH = 32,
  parameter int DWIDTH = 32,
  parameter logic [31:0] BASE_ADDR = 32'h01000000, 
  parameter int MEM_DELAY = 10
) (

  // inputs
  input logic clk,
  input logic rst,
  input logic [AWIDTH-1:0] addr_i = BASE_ADDR,
  input logic [AWIDTH-1:0] addr_dat = BASE_ADDR,
  input logic [(`BLOCK_SIZE*8)-1:0] data_dat,
  input logic read_en_i,
  input logic read_en_dat,
  input logic write_en_dat,
  input logic [2:0] funct3_i,
  input logic request, 

  // outputs
  output logic              write_finished, 
  output logic              ready, 
  output logic [DWIDTH-1:0] data_o,
  output logic [(`BLOCK_SIZE*8)-1:0] data_dat_o
);

    // Total memory size in bytes
    localparam int MEM_BYTES = (`MEM_DEPTH )* (`BLOCK_SIZE*8);  

	logic [DWIDTH-1:0] temp_memory [0:`LINE_COUNT - 1];

    // Delay Counter 
    logic [$clog2(MEM_DELAY)-1:0] delay; 

   	// Byte-addressable memory
  	logic [7:0] main_memory [0:MEM_BYTES - 1]; 
   	
    // fetch address or pc address
    logic [AWIDTH-1:0] address;

    // data memory address 
    logic [AWIDTH-1:0] address_dat; 
   	
    // Adjusted address for fetch always assume given addr_i is within range
    assign address = addr_i - BASE_ADDR; 

    // Adjusted address for data memory
    assign address_dat = (addr_dat< BASE_ADDR) ? addr_dat % MEM_BYTES:(addr_dat - BASE_ADDR) % MEM_BYTES; 
  
    int i;
 
   	initial begin

        // Initialize all main memory bytes to 0
        for (i = 0; i < MEM_BYTES; i++) begin
            main_memory[i] = 8'h00;
        end

        $readmemh(`MEM_PATH, temp_memory);

        // Load data from temp_memory into main_memory
		for (i = 0; i < `LINE_COUNT; i++) begin
       	    main_memory[4*i]     = temp_memory[i][7:0];
       		main_memory[4*i + 1] = temp_memory[i][15:8];
       		main_memory[4*i + 2] = temp_memory[i][23:16];
       		main_memory[4*i + 3] = temp_memory[i][31:24];
     	end

		$display("IMEMORY: Loaded %0d 32-bit words from %s", `LINE_COUNT, `MEM_PATH);

	end
           

    // Combinational read logic for instruction memory
	always_comb begin
	    data_o = '0; // default to zero

        if (read_en_i) begin

            if ($isunknown(addr_i)) begin
                data_o = '0;
            end 
            else if ((addr_i >= BASE_ADDR) && (addr_i + 32'd3 < BASE_ADDR + MEM_BYTES)) begin
                
                // Word-aligned fetch: little-endian assembly
                data_o = {
                          main_memory[address + 3],
                          main_memory[address + 2],
                          main_memory[address + 1],
                          main_memory[address]
                };

            end 
            else begin
                data_o = 32'hDEAD_BEEF;
                //$display("IMEMORY: OOB read @0x%08h (mapped 0x%08h)", addr_i, address);
            end
        end
  	end

    // Simulated Memory Delay 
    always_ff @(posedge clk) begin 
        if(request) begin 
            if (delay >= MEM_DELAY) begin 
                if (read_en_dat) begin 
                    ready <= 1;
                    delay<=0;
                    write_finished<=0;
                end
                if (write_en_dat) begin
                    ready <= 0;
                    delay<=0;
                    write_finished<=1;
                end
            end
            else begin
                delay <= delay + 1;
                ready <= 0; 
                write_finished <= 0; 
            end
        end
        else begin
            ready <= 0;
            delay <= 0;
            write_finished <= 0;
        end
    end
    
    // Combinational read logic for data memory
    always_comb begin
	    data_dat_o = 0; // default to zero
        if (read_en_i) begin 
            if ($isunknown(addr_dat)) begin
                data_dat_o = 0;
            end 
            else if (read_en_i) begin
                for (int i=0; i < `BLOCK_SIZE; i++) begin 
                    data_dat_o[((`BLOCK_SIZE-1)-i)*8 +: 8] = main_memory[(address_dat+(`BLOCK_SIZE - i)) % MEM_BYTES];
                end 
            end 
        end
  	end


    // Sequential write logic
    always_ff @(posedge clk) begin

        if (write_en_dat) begin 
                for (int i=0; i < `BLOCK_SIZE; i++) begin 
                main_memory[(address_dat+(`BLOCK_SIZE - i)) % MEM_BYTES] <=  data_dat[((`BLOCK_SIZE-1)-i)*8 +: 8];
            end 
        end 
        
 	end   
 
endmodule : memory

design/memory_controller.sv
/* 
    Module: Memory Controller

    Description: Memory Controller handles requests coming in from the cache and writeback buffer 
    it opportunistically preforms write backs to main memory when no active request from the cache 
    is happening. 

*/

`include "constants.svh"

module memory_controller #(
    parameter int AWIDTH = $clog2(`MEM_DEPTH),
    parameter int DWIDTH = 32
)(
    input logic reset,
    input logic clk,
    input logic [AWIDTH-1:0] addr,
    input logic rd_req,
    input logic drain_req,
    input logic [AWIDTH+DWIDTH:0] buffer_data,
    input logic pop_valid, 

    output logic pop_en,
    output logic [1:0] curr_state_out, 
    output logic ready_out, 
    output logic [DWIDTH-1:0] data_out
); 

logic [1:0] curr_state; 
logic [1:0] next_state; 



// MAIN MEMORY 
logic read_en;
logic write_en;
logic [((`BLOCK_SIZE*8)-1):0] mem_out; 
logic ready; 
logic write_finished; 
logic [((`BLOCK_SIZE*8)-1):0] mem_store;
logic [AWIDTH-1:0] store_address;  
logic request;
logic [AWIDTH-1:0] memory_address; 
memory #(
    .AWIDTH(32),
    .DWIDTH(32),
    .BASE_ADDR(32'h01000000)
    ) memory1 (
    .clk(clk),
    .rst(reset),
    .addr_i(address),
    .addr_dat(memory_address),
    .data_dat(mem_store), 
    .read_en_i(read_en),
    .read_en_dat(read_en), // controls for data memory 
    .write_en_dat(write_en),
    .funct3_i(funct3_i),
    .request(request),
    .write_finished(write_finished),
    .ready(ready),
    .data_o(),
    .data_dat_o(mem_out) // data read from data memory
);

assign ready_out = ready; 
assign curr_state_out = curr_state; 
assign data_out = mem_out; 

// STATES 
parameter IDLE = 0, READING = 1, POPPING = 2, WRITE_BACK = 3; 

// STATE LOGIC 
always_ff @(posedge clk) begin 
     if (!reset) begin 
        curr_state <= IDLE; 
    end
    else begin 
        curr_state <= next_state;  
    end 

end

// NEXT STATE LOGIC 
always_comb begin
    next_state = curr_state; // default safe value 
    unique case(curr_state) 

        IDLE: begin 

            if (rd_req) begin 
                next_state = READING; 
            end

            else if ((!rd_req) && (drain_req)) begin
                next_state = POPPING; 
            end

            else begin
                next_state = IDLE; 
            end

        end

        READING: begin
            
            if (ready) begin
                next_state = IDLE; 
            end
            else begin
                next_state = READING; 
            end

        end

        POPPING: begin 
            if (pop_valid) begin
                if ( buffer_data[AWIDTH+DWIDTH] == 0 ) begin
                    next_state = WRITE_BACK; 
                end
                else begin 
                    next_state = IDLE; 
                end
            end
            else begin
                next_state = POPPING; 
            end

        end

        WRITE_BACK: begin

            if (write_finished) begin
                next_state = IDLE; 
            end
            else begin
                next_state = WRITE_BACK; 
            end

        end

        default: next_state = curr_state; 

    endcase
end

// CONTROL LOGIC 
always_comb begin
    request = 0; 
    write_en = 0;
    read_en = 0; 
    pop_en = 0;
    memory_address = addr; 

    unique case(curr_state) 

        IDLE: begin
            request = 0; 
            read_en = 0; 
            write_en = 0; 
            pop_en = 0;
            memory_address = addr;  
        end

        READING: begin 
            request = 1; 
            write_en = 0; 
            read_en = 1; 
            pop_en = 0; 
            memory_address = addr; 
        end

        POPPING: begin
            request = 0; 
            write_en = 0;
            read_en = 0; 
            memory_address = addr;
            if (!pop_valid) begin
                pop_en = 1; 
            end  
            else begin
                pop_en = 0; 
            end
        end

        WRITE_BACK: begin
            request = 1; 
            write_en = 1;
            read_en = 0; 
            pop_en = 0;
            memory_address = store_address; 
        end

        default: begin
            request = 0; 
            write_en = 0;
            read_en = 0; 
            pop_en = 0;
            memory_address = addr; 
        end

    endcase

end

// STORE DATA LOGIC 
always_ff @(posedge clk) begin
    if (pop_valid) begin
        mem_store <= buffer_data[DWIDTH-1:0];
        store_address <= buffer_data[(AWIDTH+DWIDTH)-1:DWIDTH];  
    end
    else begin 
        mem_store <= mem_store; 
        store_address <= store_address; 
    end
end



endmodule : memory_controller

design/writeback_buffer.sv
/*
    Module: Writeback Buffer 

    Description: FIFO buffer, implemented as a circular array 
    pushes data to the tail, and pops from the head. Outputs full signal 
    for when queue is full. Dirty Cache evictions are stored here to reduce latency 
    and opportunistically drained to the memory to ensure coherence. This module 
    also searches for matching entries and returns upon hits. Stores to the same 
    address are coalesced by skipping the draining of newer entries and adding the 
    new store to the tail.  

*/

module writeback_buffer #(
    parameter int DEPTH = 8, 
    parameter int DWIDTH = 32,
    parameter int AWIDTH = 32
)(
    input logic reset, 
    input logic clk,
    input logic [(DWIDTH+AWIDTH)-1:0] push_data,
    input logic [1:0] push_pop,
    input logic [AWIDTH-1:0] search_addr,
    input logic [POINTER_BITS:0] merge_entry,
    
    output logic drain_rq, 
    output logic [POINTER_BITS:0] found_entry, 
    output logic [DWIDTH-1:0] found_data,
    output logic found,
    output logic [(DWIDTH+AWIDTH):0] pop_data,
    output logic pop_valid, 
    output logic buffer_full 
);



// Push_Pop States 
parameter NO_OP = 0, PUSH = 1, POP = 2, MERGE = 3; 

// FIFO Buffer 
logic [(DWIDTH+AWIDTH):0] fifo_buffer [0:DEPTH-1];

// Pointers 
parameter int POINTER_BITS = $clog2(DEPTH);
logic [POINTER_BITS:0] head; 
logic [POINTER_BITS:0] tail;

// Empty flag 
logic empty; 

assign drain_rq = !(empty); 

// Search Logic 
always_comb begin 
    found = 0; 
    found_entry = 0; 
    found_data = 0;

    for(int i=0; i<DEPTH; i++) begin 
        if ((fifo_buffer[i][(DWIDTH+AWIDTH)-1:DWIDTH] == search_addr) && (fifo_buffer[i][DWIDTH+AWIDTH] != 1)) begin
            found = 1; 
            found_entry = i; 
            found_data = fifo_buffer[i][DWIDTH-1:0];
        end
    end
end 


// Full and Empty Detection Logic 
always_comb begin

    if (head == tail) begin 
        empty = 1; 
        buffer_full = 0; 
    end

    else if (head[POINTER_BITS] ^ tail[POINTER_BITS]) begin 
        if (head[POINTER_BITS-1:0] == tail[POINTER_BITS-1:0]) begin
            buffer_full = 1; 
        end
        else begin
            buffer_full = 0;
        end
        empty = 0; 
    end

    else begin
        empty = 0; 
        buffer_full = 0; 
    end

end

// Push and Pop logic 
always_ff @(posedge clk) begin

    if (!reset) begin
        tail <= 0; 
        head <= 0; 
        for (int i=0; i<DEPTH; i++) begin 
            fifo_buffer[i] <= 0; 
        end 
    end

    else begin 
        unique case(push_pop)

            NO_OP:begin
                tail <= tail; 
                head <= head; 
                pop_data <= 0; 
                pop_valid <= 0; 
            end

            PUSH: begin
                if(!buffer_full) begin
                    fifo_buffer[tail[POINTER_BITS-1:0]] <= push_data;
                    tail <= tail+1; 
                end
                pop_data <= 0;
                pop_valid <= 0;  
            end

            POP: begin
                if (!empty) begin
                    pop_data <= fifo_buffer[head[POINTER_BITS-1:0]];
                    head <= head+1;
                    fifo_buffer[head[POINTER_BITS-1:0]][DWIDTH+AWIDTH] <= 1; 
                    pop_valid <= 1; 
                end
                else begin 
                    pop_data <= 0;
                    pop_valid <= 0;  
                end
            end

            MERGE: begin 
               if(!buffer_full) begin
                    fifo_buffer[tail[POINTER_BITS-1:0]] <= push_data;
                    tail <= tail+1; 
                end
                fifo_buffer[merge_entry[POINTER_BITS-1:0]][DWIDTH+AWIDTH] <= 1; 
                pop_data <= 0; 
                pop_valid <= 0; 
            end 

            default: begin
                tail <= tail; 
                head <= head; 
                pop_data <= 0;
                pop_valid <= 0; 
            end

        endcase
    end
end 


endmodule : writeback_buffer

test/fifo_tb.sv



module fifo_tb; 

logic clk; 
logic reset; 
logic [11:0] push_data; 
logic [1:0] push_pop; 
logic [3:0] search_addr;
logic [2:0] merge_entry; 

logic drain_rq; 
logic found_entry; 
logic found;
logic [12:0] pop_data; 
logic [7:0] found_data; 
logic buffer_full;
logic pop_valid; 

writeback_buffer #(
    .DEPTH(4), 
    .DWIDTH(8),
    .AWIDTH(4)
    ) fifo1 (.*); 


logic [3:0] addr; 
logic rd_req; 
logic drain_req; 
logic [12:0] buffer_data; 
assign drain_req = drain_rq; 
assign buffer_data = pop_data;
assign addr = push_data[11:8]; 

logic pop_en; 
logic curr_state_out; 
logic ready_out;
logic data_out; 
memory_controller #(
    .DWIDTH(8),
    .AWIDTH(4)
) mem1 (.*); 


initial begin 
    clk=0; 
    reset=0;
    push_data=0; 
    push_pop=0; 
    search_addr=0;
    merge_entry=0; 
    rd_req=1; 
end

always #1 clk = ~clk;

logic [1:0] push_test; 
always #1 push_pop = pop_en ? 2 : push_test; 



// simulation 
initial begin 
    $display("SIMULATION START"); 
    #3
    reset=1; 
    search_addr = 4'b1000; 
    // PUSH X
    push_test = 1; 
    push_data = 12'b100010101010;
    #2
    // PUSH Y
    push_test = 1; 
    push_data = 12'b101010101010;
    #2
    // PUSH Z
    push_test = 1; 
    push_data = 12'b100110101010;
    #2 
    // MERGE X
    push_test = 3; 
    push_data = 12'b100010100000;
    merge_entry = 3'b000; 
    #2 
    push_test = 0; 
    rd_req = 0; 

    #100

    /*
    #2
    // POP
    push_pop = 2; 
    #2 
    // PUSH A
    push_pop = 1; 
    push_data = 12'b110010101010;
    #2 
    // PUSH B
    push_pop = 1; 
    push_data = 12'b100010101010;
    #2 
    // POP
    push_pop = 2; 
    #2 
    // POP 
    push_pop = 2; 
    #2
    // POP
    push_pop = 2; 
    #2 
    // PUSH X 
    push_pop = 1; 
    push_data = 12'b100010101010;
    #2
    // MERGE X
    push_pop = 3; 
    push_data = 12'b100010100000;
    merge_entry = 3'b001;
    #2
    // MERGE X
    push_pop = 3; 
    push_data = 12'b100010111111;
    merge_entry = 3'b010;  
    #2
    */

    $finish; 
end 

initial begin 
    $dumpfile("fifo.vcd");
    $dumpvars(0, fifo_tb);  
end

endmodule

fifo.vcd
$version Generated by VerilatedVcd $end
$timescale 1ps $end
 $scope module $unit $end
  $var wire 32 e ZERO [31:0] $end
  $var wire 7 f OP_R [6:0] $end
  $var wire 7 g OP_I [6:0] $end
  $var wire 7 h OP_LOAD [6:0] $end
  $var wire 7 i OP_STORE [6:0] $end
  $var wire 7 j OP_BRANCH [6:0] $end
  $var wire 7 k OP_JALR [6:0] $end
  $var wire 7 l OP_JAL [6:0] $end
  $var wire 7 m OP_LUI [6:0] $end
  $var wire 7 n OP_AUIPC [6:0] $end
  $var wire 4 o ALU_ADD [3:0] $end
  $var wire 4 p ALU_SUB [3:0] $end
  $var wire 4 q ALU_AND [3:0] $end
  $var wire 4 r ALU_OR [3:0] $end
  $var wire 4 s ALU_XOR [3:0] $end
  $var wire 4 t ALU_SLT [3:0] $end
  $var wire 4 u ALU_SLL [3:0] $end
  $var wire 4 v ALU_SRL [3:0] $end
  $var wire 4 w ALU_SRA [3:0] $end
  $var wire 4 x ALU_LUI [3:0] $end
  $var wire 4 y ALU_BRANCH [3:0] $end
  $var wire 4 z ALU_NOP [3:0] $end
 $upscope $end
 $scope module fifo_tb $end
  $var wire 1 R clk $end
  $var wire 1 % reset $end
  $var wire 12 & push_data [11:0] $end
  $var wire 2 S push_pop [1:0] $end
  $var wire 4 ' search_addr [3:0] $end
  $var wire 3 ( merge_entry [2:0] $end
  $var wire 1 7 drain_rq $end
  $var wire 1 , found_entry $end
  $var wire 1 - found $end
  $var wire 13 8 pop_data [12:0] $end
  $var wire 8 . found_data [7:0] $end
  $var wire 1 9 buffer_full $end
  $var wire 1 : pop_valid $end
  $var wire 4 ) addr [3:0] $end
  $var wire 1 * rd_req $end
  $var wire 1 7 drain_req $end
  $var wire 13 8 buffer_data [12:0] $end
  $var wire 1 ; pop_en $end
  $var wire 1 < curr_state_out $end
  $var wire 1 = ready_out $end
  $var wire 1 / data_out $end
  $var wire 2 + push_test [1:0] $end
  $scope module fifo1 $end
   $var wire 32 V DEPTH [31:0] $end
   $var wire 32 W DWIDTH [31:0] $end
   $var wire 32 V AWIDTH [31:0] $end
   $var wire 1 % reset $end
   $var wire 1 R clk $end
   $var wire 12 & push_data [11:0] $end
   $var wire 2 S push_pop [1:0] $end
   $var wire 4 ' search_addr [3:0] $end
   $var wire 3 ( merge_entry [2:0] $end
   $var wire 1 7 drain_rq $end
   $var wire 3 0 found_entry [2:0] $end
   $var wire 8 . found_data [7:0] $end
   $var wire 1 - found $end
   $var wire 13 8 pop_data [12:0] $end
   $var wire 1 : pop_valid $end
   $var wire 1 9 buffer_full $end
   $var wire 32 X NO_OP [31:0] $end
   $var wire 32 Y PUSH [31:0] $end
   $var wire 32 Z POP [31:0] $end
   $var wire 32 [ MERGE [31:0] $end
   $var wire 13 > fifo_buffer[0] [12:0] $end
   $var wire 13 ? fifo_buffer[1] [12:0] $end
   $var wire 13 @ fifo_buffer[2] [12:0] $end
   $var wire 13 A fifo_buffer[3] [12:0] $end
   $var wire 32 \ POINTER_BITS [31:0] $end
   $var wire 3 B head [2:0] $end
   $var wire 3 C tail [2:0] $end
   $var wire 1 D empty $end
   $scope module unnamedblk1 $end
    $var wire 32 ] i [31:0] $end
   $upscope $end
   $scope module unnamedblk2 $end
    $var wire 32 E i [31:0] $end
   $upscope $end
  $upscope $end
  $scope module mem1 $end
   $var wire 32 V AWIDTH [31:0] $end
   $var wire 32 W DWIDTH [31:0] $end
   $var wire 1 % reset $end
   $var wire 1 R clk $end
   $var wire 4 ) addr [3:0] $end
   $var wire 1 * rd_req $end
   $var wire 1 7 drain_req $end
   $var wire 13 8 buffer_data [12:0] $end
   $var wire 1 : pop_valid $end
   $var wire 1 ; pop_en $end
   $var wire 2 F curr_state_out [1:0] $end
   $var wire 1 = ready_out $end
   $var wire 8 1 data_out [7:0] $end
   $var wire 2 F curr_state [1:0] $end
   $var wire 2 T next_state [1:0] $end
   $var wire 1 G read_en $end
   $var wire 1 H write_en $end
   $var wire 64 2 mem_out [63:0] $end
   $var wire 1 = ready $end
   $var wire 1 I write_finished $end
   $var wire 64 J mem_store [63:0] $end
   $var wire 4 L store_address [3:0] $end
   $var wire 1 M request $end
   $var wire 4 4 memory_address [3:0] $end
   $var wire 1 ^ address $end
   $var wire 1 _ funct3_i $end
   $var wire 32 X IDLE [31:0] $end
   $var wire 32 Y READING [31:0] $end
   $var wire 32 Z POPPING [31:0] $end
   $var wire 32 [ WRITE_BACK [31:0] $end
   $scope module memory1 $end
    $var wire 32 ` AWIDTH [31:0] $end
    $var wire 32 ` DWIDTH [31:0] $end
    $var wire 32 a BASE_ADDR [31:0] $end
    $var wire 32 b MEM_DELAY [31:0] $end
    $var wire 1 R clk $end
    $var wire 1 % rst $end
    $var wire 32 # addr_i [31:0] $end
    $var wire 32 5 addr_dat [31:0] $end
    $var wire 64 J data_dat [63:0] $end
    $var wire 1 G read_en_i $end
    $var wire 1 G read_en_dat $end
    $var wire 1 H write_en_dat $end
    $var wire 3 c funct3_i [2:0] $end
    $var wire 1 M request $end
    $var wire 1 I write_finished $end
    $var wire 1 = ready $end
    $var wire 32 N data_o [31:0] $end
    $var wire 64 2 data_dat_o [63:0] $end
    $var wire 32 d MEM_BYTES [31:0] $end
    $var wire 4 O delay [3:0] $end
    $var wire 32 $ address [31:0] $end
    $var wire 32 6 address_dat [31:0] $end
    $var wire 32 U i [31:0] $end
    $scope module unnamedblk1 $end
     $var wire 32 P i [31:0] $end
    $upscope $end
    $scope module unnamedblk2 $end
     $var wire 32 Q i [31:0] $end
    $upscope $end
   $upscope $end
  $upscope $end
 $upscope $end
$enddefinitions $end


#0
b00000000000000000000000000000000 #
b11111111000000000000000000000000 $
0%
b000000000000 &
b0000 '
b000 (
b0000 )
1*
b00 +
1,
1-
b00000000 .
0/
b011 0
b00000000 1
b0000000000000000000000000000000000000000000000000000000000000000 2
b0000 4
b00000000000000000000000000000000 5
b00000000000000000000000000000000 6
07
b0000000000000 8
09
0:
0;
0<
0=
b0000000000000 >
b0000000000000 ?
b0000000000000 @
b0000000000000 A
b000 B
b000 C
1D
b00000000000000000000000000000000 E
b00 F
0G
0H
0I
b0000000000000000000000000000000000000000000000000000000000000000 J
b0000 L
0M
b00000000000000000000000000000000 N
b0000 O
b00000000000000000000000000000000 P
b00000000000000000000000000000000 Q
0R
b00 S
b01 T
b00000000000000000000000010010011 U
b00000000000000000000000000000100 V
b00000000000000000000000000001000 W
b00000000000000000000000000000000 X
b00000000000000000000000000000001 Y
b00000000000000000000000000000010 Z
b00000000000000000000000000000011 [
b00000000000000000000000000000010 \
b00000000000000000000000000000100 ]
0^
0_
b00000000000000000000000000100000 `
b00000001000000000000000000000000 a
b00000000000000000000000000001010 b
b000 c
b00000000000010011100101000000000 d
b00000000000000000000000000000000 e
b0110011 f
b0010011 g
b0000011 h
b0100011 i
b1100011 j
b1100111 k
b1101111 l
b0110111 m
b0010111 n
b0000 o
b0001 p
b0010 q
b0011 r
b0100 s
b0101 t
b0110 u
b0111 v
b1000 w
b1001 x
b1010 y
b1111 z
#1
b00000000000000000000000000000100 E
1R
#2
0R
#3
1%
b100010101010 &
b1000 '
b1000 )
b01 +
0,
b10101010 .
b000 0
b10010000 1
b1100101111111101111011111001000011001011111111011110111110010000 2
b1000 4
b00000000000000000000000000001000 5
b00000000000000000000000000001000 6
17
1<
b0100010101010 >
b001 C
0D
b01 F
1G
1M
b11011110101011011011111011101111 N
b00000000000000000000000000001000 P
1R
b01 S
#4
0R
#5
b101010101010 &
b1010 )
1/
b11111101 1
b1110111110010000110010111111110111101111100100001100101111111101 2
b1010 4
b00000000000000000000000000001010 5
b00000000000000000000000000001010 6
b0101010101010 ?
b010 C
b0001 O
1R
#6
0R
#7
b100110101010 &
b1001 )
b11101111 1
b1001000011001011111111011110111110010000110010111111110111101111 2
b1001 4
b00000000000000000000000000001001 5
b00000000000000000000000000001001 6
b0100110101010 @
b011 C
b0010 O
1R
#8
0R
#9
b100010100000 &
b1000 )
b11 +
1,
b10100000 .
0/
b011 0
b10010000 1
b1100101111111101111011111001000011001011111111011110111110010000 2
b1000 4
b00000000000000000000000000001000 5
b00000000000000000000000000001000 6
19
b1100010101010 >
b0100010100000 A
b100 C
b0011 O
1R
b11 S
#10
0R
#11
0*
b00 +
b0100 O
1R
b00 S
#12
0R
#13
b0101 O
1R
#14
0R
#15
b0110 O
1R
#16
0R
#17
b0111 O
1R
#18
0R
#19
b1000 O
1R
#20
0R
#21
b1001 O
1R
#22
0R
#23
b1010 O
1R
#24
0R
#25
1=
b0000 O
1R
b00 T
#26
0R
#27
b00000000 1
b0000000000000000000000000000000000000000000000000000000000000000 2
0<
0=
b00 F
0G
0M
b00000000000000000000000000000000 N
b0001 O
1R
b10 T
#28
0R
#29
1;
b10 F
b0000 O
1R
#30
0R
b10 S
#31
b1100010101010 8
09
1:
0;
b001 B
1R
b00 T
#32
0R
b00 S
#33
b0000000000000 8
0:
b00 F
b0000000000000000000000000000000000000000000000000000000010101010 J
b1000 L
1R
b10 T
#34
0R
#35
1;
b10 F
1R
#36
0R
b10 S
#37
b0101010101010 8
1:
0;
b1101010101010 ?
b010 B
1R
b11 T
#38
0R
b00 S
#39
b1010 4
b00000000000000000000000000001010 5
b00000000000000000000000000001010 6
b0000000000000 8
0:
1<
b11 F
1H
b1010 L
1M
1R
#40
0R
#41
b0001 O
b00000000000000000000000000001000 Q
1R
#42
0R
#43
b0010 O
1R
#44
0R
#45
b0011 O
1R
#46
0R
#47
b0100 O
1R
#48
0R
#49
b0101 O
1R
#50
0R
#51
b0110 O
1R
#52
0R
#53
b0111 O
1R
#54
0R
#55
b1000 O
1R
#56
0R
#57
b1001 O
1R
#58
0R
#59
b1010 O
1R
#60
0R
#61
1I
b0000 O
1R
b00 T
#62
0R
#63
b1000 4
b00000000000000000000000000001000 5
b00000000000000000000000000001000 6
0<
b00 F
0H
0I
0M
b0001 O
1R
b10 T
#64
0R
#65
1;
b10 F
b0000 O
1R
#66
0R
b10 S
#67
b0100110101010 8
1:
0;
b1100110101010 @
b011 B
1R
b11 T
#68
0R
b00 S
#69
b1001 4
b00000000000000000000000000001001 5
b00000000000000000000000000001001 6
b0000000000000 8
0:
1<
b11 F
1H
b1001 L
1M
1R
#70
0R
#71
b0001 O
1R
#72
0R
#73
b0010 O
1R
#74
0R
#75
b0011 O
1R
#76
0R
#77
b0100 O
1R
#78
0R
#79
b0101 O
1R
#80
0R
#81
b0110 O
1R
#82
0R
#83
b0111 O
1R
#84
0R
#85
b1000 O
1R
#86
0R
#87
b1001 O
1R
#88
0R
#89
b1010 O
1R
#90
0R
#91
1I
b0000 O
1R
b00 T
#92
0R
#93
b1000 4
b00000000000000000000000000001000 5
b00000000000000000000000000001000 6
0<
b00 F
0H
0I
0M
b0001 O
1R
b10 T
#94
0R
#95
1;
b10 F
b0000 O
1R
#96
0R
b10 S
#97
0,
0-
b00000000 .
b000 0
07
b0100010100000 8
1:
0;
b1100010100000 A
b100 B
1D
1R
b11 T
#98
0R
b00 S
#99
b0000000000000 8
0:
1<
b11 F
1H
b0000000000000000000000000000000000000000000000000000000010100000 J
b1000 L
1M
1R
#100
0R
#101
b0001 O
1R
#102
0R
#103
b0010 O
1R
#104
0R
#105
b0011 O
1R
#106
0R
#107
b0100 O
1R
#108
0R
#109
b0101 O
1R
#110
0R
#111
b0110 O
1R
