design/fifo_buffer.sv
/*
    Module: FIFO Buffer 

    Description: Reusable FIFO buffer, implemented as a circular array 
    pushes data to the tail, and pops from the head. Outputs full signal 
    for when queue is full. 

*/

module fifo_buffer #(
    parameter int DEPTH = 8, 
    parameter int DWIDTH = 32
)(
    input logic [DWIDTH-1:0] push_data,
    input logic [1:0] push_pop,
    input logic reset, 
    input logic clk,

    output logic [DWIDTH-1:0] pop_data,
    output logic buffer_full 
);

// Push_Pop States 
parameter NO_OP = 0, PUSH = 1, POP = 2; 

// FIFO Buffer 
logic [DWIDTH-1:0] fifo_buffer [0:DEPTH-1];

// Pointers 
parameter int POINTER_BITS = $clog2(DEPTH);
logic [POINTER_BITS:0] head; 
logic [POINTER_BITS:0] tail;

// Empty flag 
logic empty; 


// Full and Empty Detection Logic 
always_comb begin

    if (head == tail) begin 
        empty = 1; 
        buffer_full = 0; 
    end

    else if (head[POINTER_BITS] ^ tail[POINTER_BITS]) begin 
        if (head[POINTER_BITS-1:0] == tail[POINTER_BITS-1:0]) begin
            buffer_full = 1; 
        end
        else begin
            buffer_full = 0;
        end
        empty = 0; 
    end

    else begin
        empty = 0; 
        buffer_full = 0; 
    end

end

// Push and Pop logic 
always_ff @(posedge clk) begin

    if (!reset) begin
        tail <= 0; 
        head <= 0; 
    end

    else begin 
        unique case(push_pop)

            NO_OP:begin
                tail <= tail; 
                head <= head; 
                pop_data <= 0; 
            end

            PUSH: begin
                if(!buffer_full) begin
                    fifo_buffer[tail] <= push_data;
                    tail <= tail+1; 
                end
                pop_data <= 0; 
            end

            POP: begin
                if (!empty) begin
                    pop_data <= fifo_buffer[head];
                    head <= head+1; 
                end
                else begin 
                    pop_data <= 0; 
                end
            end

            default: begin
                tail <= tail; 
                head <= head; 
                pop_data <= 0;
            end

        endcase
    end
end 


endmodule : fifo_buffer

test/fifo_tb.sv



module fifo_tb; 

logic clk; 
logic reset; 
logic [7:0] push_data; 
logic [1:0] push_pop; 
logic [7:0] pop_data; 
logic buffer_full; 


fifo_buffer #(
    .DEPTH(4), 
    .DWIDTH(8)
    ) fifo1 (.*); 


initial begin 
    clk=0; 
    reset=0;
    push_data=0; 
    push_pop=0;   
end

always #1 clk = ~clk;



// simulation 
initial begin 
    $display("SIMULATION START"); 
    #5
    reset=1; 
    #5
    push_data = 3; 
    push_pop = 1;
    #10
    push_pop = 2; 
    #100
    $finish; 
end 

initial begin 
    $dumpfile("fifo.vcd");
    $dumpvars(0, fifo_tb);  
end

endmodule

fifo.vcd
$version Generated by VerilatedVcd $end
$timescale 1ps $end
 $scope module fifo_tb $end
  $var wire 1 , clk $end
  $var wire 1 - reset $end
  $var wire 8 . push_data [7:0] $end
  $var wire 2 / push_pop [1:0] $end
  $var wire 8 # pop_data [7:0] $end
  $var wire 1 $ buffer_full $end
  $scope module fifo1 $end
   $var wire 32 0 DEPTH [31:0] $end
   $var wire 32 1 DWIDTH [31:0] $end
   $var wire 8 . push_data [7:0] $end
   $var wire 2 / push_pop [1:0] $end
   $var wire 1 - reset $end
   $var wire 1 , clk $end
   $var wire 8 # pop_data [7:0] $end
   $var wire 1 $ buffer_full $end
   $var wire 32 2 NO_OP [31:0] $end
   $var wire 32 3 PUSH [31:0] $end
   $var wire 32 4 POP [31:0] $end
   $var wire 8 % fifo_buffer[0] [7:0] $end
   $var wire 8 & fifo_buffer[1] [7:0] $end
   $var wire 8 ' fifo_buffer[2] [7:0] $end
   $var wire 8 ( fifo_buffer[3] [7:0] $end
   $var wire 32 5 POINTER_BITS [31:0] $end
   $var wire 3 ) head [2:0] $end
   $var wire 3 * tail [2:0] $end
   $var wire 1 + empty $end
  $upscope $end
 $upscope $end
$enddefinitions $end


#0
b00000000 #
0$
b00000000 %
b00000000 &
b00000000 '
b00000000 (
b000 )
b000 *
1+
0,
0-
b00000000 .
b00 /
b00000000000000000000000000000100 0
b00000000000000000000000000001000 1
b00000000000000000000000000000000 2
b00000000000000000000000000000001 3
b00000000000000000000000000000010 4
b00000000000000000000000000000010 5
#1
1,
#2
0,
#3
1,
#4
0,
#5
1,
1-
#6
0,
#7
1,
#8
0,
#9
1,
#10
0,
b00000011 .
b01 /
#11
b00000011 %
b001 *
0+
1,
#12
0,
#13
b00000011 &
b010 *
1,
#14
0,
#15
b00000011 '
b011 *
1,
#16
0,
#17
1$
b00000011 (
b100 *
1,
#18
0,
#19
1,
#20
0,
b10 /
#21
b00000011 #
0$
b001 )
1,
#22
0,
#23
b010 )
1,
#24
0,
#25
b011 )
1,
#26
0,
#27
b100 )
1+
1,
#28
0,
#29
b00000000 #
1,
